drone_teaching_package/__init__.py
drone_teaching_package/real_tello.py
drone_teaching_package/simulated_tello.py
my_drone_package-0.1.dist-info/LICENSE
my_drone_package-0.1.dist-info/METADATA
my_drone_package-0.1.dist-info/WHEEL
my_drone_package-0.1.dist-info/top_level.txt
my_drone_package-0.1.dist-info/RECORD
