Metadata-Version: 2.1
Name: my_drone_package
Version: 0.1
Summary: A package for controlling a drone either via simulation or with a real Tello drone.
Home-page: https://github.com/bhavyabgada/drone_teaching_package
Author: Bhavya Bipin Gada
Author-email: bgada1@umbc.edu
Classifier: Programming Language :: Python :: 3
Classifier: License :: OSI Approved :: MIT License
Classifier: Operating System :: OS Independent
Requires-Python: >=3.6
License-File: LICENSE
Requires-Dist: DroneBlocksTelloSimulator
Requires-Dist: easytello
